main.py
companyhunter-1.0.0.dist-info/LICENSE
companyhunter-1.0.0.dist-info/METADATA
companyhunter-1.0.0.dist-info/WHEEL
companyhunter-1.0.0.dist-info/entry_points.txt
companyhunter-1.0.0.dist-info/top_level.txt
companyhunter-1.0.0.dist-info/RECORD
