Metadata-Version: 2.1
Name: companyhunter
Version: 1.0.0
Summary: Find company emails from the web.
Author-email: Ulas Can Zorer <ulascanzorer@gmail.com>
License: Copyright © 2023 <copyright holders>
Project-URL: Homepage, https://github.com/ulascanzorer/companyhunter
Classifier: License :: OSI Approved :: MIT License
Classifier: Programming Language :: Python
Classifier: Programming Language :: Python :: 3
Requires-Python: >=3.9
License-File: LICENSE
Requires-Dist: googlesearch-python (>=1.2.3)
Requires-Dist: requests-html (>=0.10.0)
Requires-Dist: bs4 (>=0.0.1)
Requires-Dist: urllib3 (>=1.26.5)
Provides-Extra: dev
Requires-Dist: black ; extra == 'dev'
Requires-Dist: bumpver ; extra == 'dev'
Requires-Dist: isort ; extra == 'dev'
Requires-Dist: pip-tools ; extra == 'dev'
Requires-Dist: pytest ; extra == 'dev'
